shanmukh_package/__init__.py
shanmukh_package/module.py
shanmukh_package/data/Users.csv
yrt_7895pckge/__init__.py
yrt_7895pckge/module.py
yrt_7895pckge/data/Users.csv
shanmukh_package-0.1.dist-info/METADATA
shanmukh_package-0.1.dist-info/WHEEL
shanmukh_package-0.1.dist-info/entry_points.txt
shanmukh_package-0.1.dist-info/top_level.txt
shanmukh_package-0.1.dist-info/RECORD
